py_vibracore-0.3.1.dist-info/licenses/LICENSE
pyvibracore/__init__.py
pyvibracore/_version.py
pyvibracore/api.py
pyvibracore/input/__init__.py
pyvibracore/input/constants.py
pyvibracore/input/impact_force_properties.py
pyvibracore/input/vibration_properties.py
pyvibracore/results/__init__.py
pyvibracore/results/impact_force_result.py
pyvibracore/results/nuisance.py
pyvibracore/results/plot_utils.py
pyvibracore/results/sound_result.py
pyvibracore/results/vibration_result.py
py_vibracore-0.3.1.dist-info/METADATA
py_vibracore-0.3.1.dist-info/WHEEL
py_vibracore-0.3.1.dist-info/top_level.txt
py_vibracore-0.3.1.dist-info/RECORD
