Metadata-Version: 2.4
Name: py-vibracore
Version: 0.3.1
Summary: Public python SDK for the CEMS VibraCore web-API.
License: MIT License
Project-URL: repository, https://github.com/cemsbv/py-vibracore
Keywords: API,VibraCore,CEMS,CRUX
Requires-Python: >=3.11
License-File: LICENSE
Requires-Dist: pygef<0.12,>=0.11.1
Requires-Dist: cems-nuclei[client]<4,>=3.0.0
Requires-Dist: geopandas<2,>=1.0.1
Requires-Dist: pyogrio<0.11,>=0.10.0
Requires-Dist: scipy<2,>=1.15.2
Provides-Extra: test
Requires-Dist: coveralls; extra == "test"
Requires-Dist: pytest; extra == "test"
Requires-Dist: requests-mock; extra == "test"
Provides-Extra: docs
Requires-Dist: Sphinx==8.2.3; extra == "docs"
Requires-Dist: sphinx-autodoc-typehints==3.1.0; extra == "docs"
Requires-Dist: ipython==9.1.0; extra == "docs"
Requires-Dist: asteroid-sphinx-theme==0.0.3; extra == "docs"
Requires-Dist: sphinx_rtd_theme==3.0.2; extra == "docs"
Provides-Extra: lint
Requires-Dist: ansible-lint==25.1.3; extra == "lint"
Requires-Dist: black==25.1.0; extra == "lint"
Requires-Dist: cfn-lint==1.25.1; extra == "lint"
Requires-Dist: cpplint==2.0.0; extra == "lint"
Requires-Dist: flake8==7.1.2; extra == "lint"
Requires-Dist: isort==6.0.0; extra == "lint"
Requires-Dist: mypy==1.15.0; extra == "lint"
Requires-Dist: sqlfluff==3.3.1; extra == "lint"
Requires-Dist: yamllint==1.35.1; extra == "lint"
Requires-Dist: yq==3.4.3; extra == "lint"
Provides-Extra: notebook
Requires-Dist: contextily<2,>=1.6.2; extra == "notebook"
Requires-Dist: tqdm[notebook]<5,>=4.67.1; extra == "notebook"
Requires-Dist: ipympl<0.10,>=0.9.7; extra == "notebook"
Requires-Dist: fiona<2,>=1.10.1; extra == "notebook"
Dynamic: license-file
